[
  {
    "id": "8343",
    "wojewodztwo_id": "13",
    "miejscowosc_id": "2999",
    "miejscowosc": "Dzia\u0142oszyce",
    "typ": "gimnazjum",
    "nazwa": "Gimnazjum ",
    "ulica": "Szkolna",
    "numer": "5",
    "kod": "28-440",
    "poczta": "Dzia\u0142oszyce\r"
  },
  {
    "id": "8344",
    "wojewodztwo_id": "13",
    "miejscowosc_id": "2999",
    "miejscowosc": "Dzia\u0142oszyce",
    "typ": "podstawowa",
    "nazwa": "Szko\u0142a Podstawowa ",
    "ulica": "Szkolna",
    "numer": "5",
    "kod": "28-440",
    "poczta": "Dzia\u0142oszyce\r"
  }
]