[
  {
    "id": "19215",
    "wojewodztwo_id": "15",
    "miejscowosc_id": "6858",
    "miejscowosc": "Rogalinek",
    "typ": "gimnazjum",
    "nazwa": "Gimnazjum ",
    "ulica": "Pozna\u0144ska",
    "numer": "19",
    "kod": "62-022",
    "poczta": "Rogalinek\r"
  },
  {
    "id": "19216",
    "wojewodztwo_id": "15",
    "miejscowosc_id": "6858",
    "miejscowosc": "Rogalinek",
    "typ": "podstawowa",
    "nazwa": "Szko\u0142a Podstawowa im. A. Wodziczki ",
    "ulica": "Pozna\u0144ska",
    "numer": "19",
    "kod": "62-022",
    "poczta": "Rogalinek\r"
  }
]