[
  {
    "id": "22874",
    "wojewodztwo_id": "7",
    "miejscowosc_id": "8235",
    "miejscowosc": "Ciechan\u00f3w",
    "typ": "gimnazjum",
    "nazwa": "Gimnazjum Nr 1",
    "ulica": "Orylska",
    "numer": "3",
    "kod": "06-400",
    "poczta": "Ciechan\u00f3w\r"
  },
  {
    "id": "22886",
    "wojewodztwo_id": "7",
    "miejscowosc_id": "8235",
    "miejscowosc": "Ciechan\u00f3w",
    "typ": "gimnazjum",
    "nazwa": "Gimnazjum Nr 2",
    "ulica": "Powsta\u0144c\u00f3w Wielkopolskich",
    "numer": "1",
    "kod": "06-413",
    "poczta": "Ciechan\u00f3w\r"
  },
  {
    "id": "22875",
    "wojewodztwo_id": "7",
    "miejscowosc_id": "8235",
    "miejscowosc": "Ciechan\u00f3w",
    "typ": "gimnazjum",
    "nazwa": "Gimnazjum Nr 3",
    "ulica": "17 Stycznia",
    "numer": "17",
    "kod": "06-400",
    "poczta": "Ciechan\u00f3w\r"
  },
  {
    "id": "22876",
    "wojewodztwo_id": "7",
    "miejscowosc_id": "8235",
    "miejscowosc": "Ciechan\u00f3w",
    "typ": "gimnazjum",
    "nazwa": "Gimnazjum TWP",
    "ulica": "Kraszewskiego",
    "numer": "8a",
    "kod": "06-400",
    "poczta": "Ciechan\u00f3w\r"
  },
  {
    "id": "22888",
    "wojewodztwo_id": "7",
    "miejscowosc_id": "8235",
    "miejscowosc": "Ciechan\u00f3w",
    "typ": "gimnazjum",
    "nazwa": "Gimnazjum z Oddzia\u0142ami Integracyjnymi Nr 4",
    "ulica": "Czarnieckiego",
    "numer": "40",
    "kod": "06-400",
    "poczta": "Ciechan\u00f3w\r"
  },
  {
    "id": "22878",
    "wojewodztwo_id": "7",
    "miejscowosc_id": "8235",
    "miejscowosc": "Ciechan\u00f3w",
    "typ": "ponadgimnazjalna",
    "nazwa": "I Liceum Og\u00f3lnokszta\u0142c\u0105ce",
    "ulica": "17 Stycznia",
    "numer": "66",
    "kod": "06-400",
    "poczta": "Ciechan\u00f3w\r"
  },
  {
    "id": "22879",
    "wojewodztwo_id": "7",
    "miejscowosc_id": "8235",
    "miejscowosc": "Ciechan\u00f3w",
    "typ": "ponadgimnazjalna",
    "nazwa": "I Liceum Og\u00f3lnokszta\u0142c\u0105ce PUL ",
    "ulica": "Orylska",
    "numer": "3",
    "kod": "06-400",
    "poczta": "Ciechan\u00f3w\r"
  },
  {
    "id": "22890",
    "wojewodztwo_id": "7",
    "miejscowosc_id": "8235",
    "miejscowosc": "Ciechan\u00f3w",
    "typ": "ponadgimnazjalna",
    "nazwa": "II Liceum Og\u00f3lnokszta\u0142c\u0105ce",
    "ulica": "Orylska",
    "numer": "9",
    "kod": "06-400",
    "poczta": "Ciechan\u00f3w\r"
  },
  {
    "id": "22893",
    "wojewodztwo_id": "7",
    "miejscowosc_id": "8235",
    "miejscowosc": "Ciechan\u00f3w",
    "typ": "ponadgimnazjalna",
    "nazwa": "III Liceum Og\u00f3lnokszta\u0142c\u0105ce",
    "ulica": "Okrzei",
    "numer": "6",
    "kod": "06-400",
    "poczta": "Ciechan\u00f3w\r"
  },
  {
    "id": "22896",
    "wojewodztwo_id": "7",
    "miejscowosc_id": "8235",
    "miejscowosc": "Ciechan\u00f3w",
    "typ": "ponadgimnazjalna",
    "nazwa": "IV Liceum Og\u00f3lnokszta\u0142c\u0105ce",
    "ulica": "Powsta\u0144c\u00f3w Warszawskich",
    "numer": "24",
    "kod": "06-400",
    "poczta": "Ciechan\u00f3w\r"
  },
  {
    "id": "22880",
    "wojewodztwo_id": "7",
    "miejscowosc_id": "8235",
    "miejscowosc": "Ciechan\u00f3w",
    "typ": "ponadgimnazjalna",
    "nazwa": "Liceum Og\u00f3lnokszta\u0142c\u0105ce",
    "ulica": "Kraszewskiego",
    "numer": "8 a",
    "kod": "06-400",
    "poczta": "Ciechan\u00f3w\r"
  },
  {
    "id": "22885",
    "wojewodztwo_id": "7",
    "miejscowosc_id": "8235",
    "miejscowosc": "Ciechan\u00f3w",
    "typ": "ponadgimnazjalna",
    "nazwa": "Liceum Og\u00f3lnokszta\u0142c\u0105ce",
    "ulica": "P\u0142o\u0144ska",
    "numer": "57a",
    "kod": "06-400",
    "poczta": "Ciechan\u00f3w\r"
  },
  {
    "id": "22881",
    "wojewodztwo_id": "7",
    "miejscowosc_id": "8235",
    "miejscowosc": "Ciechan\u00f3w",
    "typ": "ponadgimnazjalna",
    "nazwa": "Liceum Og\u00f3lnokszta\u0142c\u0105ce Akademickiego Centrum Kszta\u0142cenia przy PWSZ",
    "ulica": "Sienkiewicza",
    "numer": "28a",
    "kod": "06-400",
    "poczta": "Ciechan\u00f3w\r"
  },
  {
    "id": "22882",
    "wojewodztwo_id": "7",
    "miejscowosc_id": "8235",
    "miejscowosc": "Ciechan\u00f3w",
    "typ": "ponadgimnazjalna",
    "nazwa": "Liceum Profilowane",
    "ulica": "Kraszewskiego",
    "numer": "8 a",
    "kod": "06-400",
    "poczta": "Ciechan\u00f3w\r"
  },
  {
    "id": "22872",
    "wojewodztwo_id": "7",
    "miejscowosc_id": "8235",
    "miejscowosc": "Ciechan\u00f3w",
    "typ": "podstawowa",
    "nazwa": "Spo\u0142eczna Szko\u0142a Podstawowa Spo\u0142ecznego Towarzystwa O\u015bwiatowego",
    "ulica": "Wyspia\u0144skiego",
    "numer": "11a",
    "kod": "06-400",
    "poczta": "Ciechan\u00f3w\r"
  },
  {
    "id": "22877",
    "wojewodztwo_id": "7",
    "miejscowosc_id": "8235",
    "miejscowosc": "Ciechan\u00f3w",
    "typ": "gimnazjum",
    "nazwa": "Spo\u0142eczne Gimnazjum Spo\u0142ecznego Towarzystwa O\u015bwiatowego ",
    "ulica": "Wyspia\u0144skiego",
    "numer": "11A",
    "kod": "06-400",
    "poczta": "Ciechan\u00f3w\r"
  },
  {
    "id": "22887",
    "wojewodztwo_id": "7",
    "miejscowosc_id": "8235",
    "miejscowosc": "Ciechan\u00f3w",
    "typ": "podstawowa",
    "nazwa": "Szko\u0142a Podstawowa Nr 3",
    "ulica": "Powsta\u0144c\u00f3w Wielkopolskich",
    "numer": "1",
    "kod": "06-413",
    "poczta": "Ciechan\u00f3w\r"
  },
  {
    "id": "22869",
    "wojewodztwo_id": "7",
    "miejscowosc_id": "8235",
    "miejscowosc": "Ciechan\u00f3w",
    "typ": "podstawowa",
    "nazwa": "Szko\u0142a Podstawowa Nr 4",
    "ulica": "P\u0142o\u0144ska",
    "numer": "143",
    "kod": "06-400",
    "poczta": "Ciechan\u00f3w\r"
  },
  {
    "id": "22870",
    "wojewodztwo_id": "7",
    "miejscowosc_id": "8235",
    "miejscowosc": "Ciechan\u00f3w",
    "typ": "podstawowa",
    "nazwa": "Szko\u0142a Podstawowa Nr 5 im. W\u0142. Broniewskiego",
    "ulica": "Broniewskiego",
    "numer": "1",
    "kod": "06-400",
    "poczta": "Ciechan\u00f3w\r"
  },
  {
    "id": "22871",
    "wojewodztwo_id": "7",
    "miejscowosc_id": "8235",
    "miejscowosc": "Ciechan\u00f3w",
    "typ": "podstawowa",
    "nazwa": "Szko\u0142a Podstawowa Nr 6",
    "ulica": "Wiklinowa",
    "numer": "4",
    "kod": "06-400",
    "poczta": "Ciechan\u00f3w\r"
  },
  {
    "id": "22873",
    "wojewodztwo_id": "7",
    "miejscowosc_id": "8235",
    "miejscowosc": "Ciechan\u00f3w",
    "typ": "podstawowa",
    "nazwa": "Szko\u0142a Podstawowa TWP",
    "ulica": "Kraszewskiego",
    "numer": "8A",
    "kod": "06-400",
    "poczta": "Ciechan\u00f3w\r"
  },
  {
    "id": "22889",
    "wojewodztwo_id": "7",
    "miejscowosc_id": "8235",
    "miejscowosc": "Ciechan\u00f3w",
    "typ": "podstawowa",
    "nazwa": "Szko\u0142a Podstawowa z Oddzia\u0142ami Integracyjnymi Nr 7",
    "ulica": "Czarnieckiego",
    "numer": "40",
    "kod": "06-400",
    "poczta": "Ciechan\u00f3w\r"
  },
  {
    "id": "22883",
    "wojewodztwo_id": "7",
    "miejscowosc_id": "8235",
    "miejscowosc": "Ciechan\u00f3w",
    "typ": "ponadgimnazjalna",
    "nazwa": "Szko\u0142a Techniczna Zespo\u0142u Szk\u00f3\u0142 BZDZ",
    "ulica": "Powsta\u0144c\u00f3w Wielkopolskich",
    "numer": "1",
    "kod": "06-413",
    "poczta": "Ciechan\u00f3w\r"
  },
  {
    "id": "22884",
    "wojewodztwo_id": "7",
    "miejscowosc_id": "8235",
    "miejscowosc": "Ciechan\u00f3w",
    "typ": "ponadgimnazjalna",
    "nazwa": "Technikum Akademickiego Centrum Kszta\u0142cenia przy PWSZ",
    "ulica": "Sienkiewicza",
    "numer": "28a",
    "kod": "06-400",
    "poczta": "Ciechan\u00f3w\r"
  },
  {
    "id": "22897",
    "wojewodztwo_id": "7",
    "miejscowosc_id": "8235",
    "miejscowosc": "Ciechan\u00f3w",
    "typ": "ponadgimnazjalna",
    "nazwa": "Technikum Nr 1",
    "ulica": "Powsta\u0144c\u00f3w Warszawskich",
    "numer": "24",
    "kod": "06-400",
    "poczta": "Ciechan\u00f3w\r"
  },
  {
    "id": "22891",
    "wojewodztwo_id": "7",
    "miejscowosc_id": "8235",
    "miejscowosc": "Ciechan\u00f3w",
    "typ": "ponadgimnazjalna",
    "nazwa": "Technikum Nr 2",
    "ulica": "Orylska",
    "numer": "9",
    "kod": "06-400",
    "poczta": "Ciechan\u00f3w\r"
  },
  {
    "id": "22894",
    "wojewodztwo_id": "7",
    "miejscowosc_id": "8235",
    "miejscowosc": "Ciechan\u00f3w",
    "typ": "ponadgimnazjalna",
    "nazwa": "Technikum Nr 3",
    "ulica": "Okrzei",
    "numer": "6",
    "kod": "06-400",
    "poczta": "Ciechan\u00f3w\r"
  },
  {
    "id": "22898",
    "wojewodztwo_id": "7",
    "miejscowosc_id": "8235",
    "miejscowosc": "Ciechan\u00f3w",
    "typ": "ponadgimnazjalna",
    "nazwa": "Technikum Nr 4",
    "ulica": "Kopernika",
    "numer": "7",
    "kod": "06-400",
    "poczta": "Ciechan\u00f3w\r"
  },
  {
    "id": "22892",
    "wojewodztwo_id": "7",
    "miejscowosc_id": "8235",
    "miejscowosc": "Ciechan\u00f3w",
    "typ": "ponadgimnazjalna",
    "nazwa": "Zasadnicza Szko\u0142a Zawodowa Nr 2",
    "ulica": "Orylska",
    "numer": "9",
    "kod": "06-400",
    "poczta": "Ciechan\u00f3w\r"
  },
  {
    "id": "22895",
    "wojewodztwo_id": "7",
    "miejscowosc_id": "8235",
    "miejscowosc": "Ciechan\u00f3w",
    "typ": "ponadgimnazjalna",
    "nazwa": "Zasadnicza Szko\u0142a Zawodowa Nr 3",
    "ulica": "Okrzei",
    "numer": "6",
    "kod": "06-400",
    "poczta": "Ciechan\u00f3w\r"
  },
  {
    "id": "22899",
    "wojewodztwo_id": "7",
    "miejscowosc_id": "8235",
    "miejscowosc": "Ciechan\u00f3w",
    "typ": "ponadgimnazjalna",
    "nazwa": "Zasadnicza Szko\u0142a Zawodowa Nr 4",
    "ulica": "Kopernika",
    "numer": "7",
    "kod": "06-400",
    "poczta": "Ciechan\u00f3w\r"
  }
]