[
  {
    "id": "25402",
    "wojewodztwo_id": "7",
    "miejscowosc_id": "9317",
    "miejscowosc": "Radom",
    "typ": "gimnazjum",
    "nazwa": "Gimnazjum Towarzystwa Wiedzy Powszechnej",
    "ulica": "Traugutta",
    "numer": "44",
    "kod": "26-600",
    "poczta": "Radom\r"
  },
  {
    "id": "25411",
    "wojewodztwo_id": "7",
    "miejscowosc_id": "9317",
    "miejscowosc": "Radom",
    "typ": "ponadgimnazjalna",
    "nazwa": "I Liceum Og\u00f3lnokszta\u0142c\u0105ce",
    "ulica": "\u017beromskiego",
    "numer": "10",
    "kod": "26-600",
    "poczta": "Radom\r"
  },
  {
    "id": "25420",
    "wojewodztwo_id": "7",
    "miejscowosc_id": "9317",
    "miejscowosc": "Radom",
    "typ": "ponadgimnazjalna",
    "nazwa": "I Liceum Og\u00f3lnokszta\u0142c\u0105ce CN-B",
    "ulica": "Ko\u015bciuszki",
    "numer": "7",
    "kod": "26-600",
    "poczta": "Radom\r"
  },
  {
    "id": "25389",
    "wojewodztwo_id": "7",
    "miejscowosc_id": "9317",
    "miejscowosc": "Radom",
    "typ": "podstawowa",
    "nazwa": "I Spo\u0142eczna Szko\u0142a Podstawowa STO",
    "ulica": "Piwnika",
    "numer": "3",
    "kod": "26-600",
    "poczta": "Radom\r"
  },
  {
    "id": "25421",
    "wojewodztwo_id": "7",
    "miejscowosc_id": "9317",
    "miejscowosc": "Radom",
    "typ": "ponadgimnazjalna",
    "nazwa": "I Spo\u0142eczne Liceum Og\u00f3lnokszta\u0142c\u0105ce STO",
    "ulica": "Sandomierska",
    "numer": "20",
    "kod": "26-600",
    "poczta": "Radom\r"
  },
  {
    "id": "25412",
    "wojewodztwo_id": "7",
    "miejscowosc_id": "9317",
    "miejscowosc": "Radom",
    "typ": "ponadgimnazjalna",
    "nazwa": "II Liceum Og\u00f3lnokszta\u0142c\u0105ce",
    "ulica": "Kusoci\u0144skiego",
    "numer": "8",
    "kod": "26-600",
    "poczta": "Radom\r"
  },
  {
    "id": "25403",
    "wojewodztwo_id": "7",
    "miejscowosc_id": "9317",
    "miejscowosc": "Radom",
    "typ": "gimnazjum",
    "nazwa": "II Spo\u0142eczne Gimnazjum STO",
    "ulica": "Sandomierska",
    "numer": "20",
    "kod": "26-600",
    "poczta": "Radom\r"
  },
  {
    "id": "25413",
    "wojewodztwo_id": "7",
    "miejscowosc_id": "9317",
    "miejscowosc": "Radom",
    "typ": "ponadgimnazjalna",
    "nazwa": "III Liceum Og\u00f3lnokszta\u0142c\u0105ce",
    "ulica": "Traugutta",
    "numer": "44",
    "kod": "26-600",
    "poczta": "Radom\r"
  },
  {
    "id": "25414",
    "wojewodztwo_id": "7",
    "miejscowosc_id": "9317",
    "miejscowosc": "Radom",
    "typ": "ponadgimnazjalna",
    "nazwa": "IV Liceum Og\u00f3lnokszta\u0142c\u0105ce z Oddzia\u0142ami Dwuj\u0119zycznymi",
    "ulica": "Mariacka",
    "numer": "25",
    "kod": "26-600",
    "poczta": "Radom\r"
  },
  {
    "id": "25447",
    "wojewodztwo_id": "7",
    "miejscowosc_id": "9317",
    "miejscowosc": "Radom",
    "typ": "ponadgimnazjalna",
    "nazwa": "IX Liceum Og\u00f3lnokszta\u0142c\u0105ce",
    "ulica": "Staromiejska",
    "numer": "11",
    "kod": "26-600",
    "poczta": "Radom\r"
  },
  {
    "id": "25404",
    "wojewodztwo_id": "7",
    "miejscowosc_id": "9317",
    "miejscowosc": "Radom",
    "typ": "gimnazjum",
    "nazwa": "Katolickie Gimnazjum",
    "ulica": "Grzybowska",
    "numer": "22",
    "kod": "26-600",
    "poczta": "Radom\r"
  },
  {
    "id": "25422",
    "wojewodztwo_id": "7",
    "miejscowosc_id": "9317",
    "miejscowosc": "Radom",
    "typ": "ponadgimnazjalna",
    "nazwa": "Katolickie Liceum Og\u00f3lnokszta\u0142c\u0105ce",
    "ulica": "Grzybowska",
    "numer": "22",
    "kod": "26-600",
    "poczta": "Radom\r"
  },
  {
    "id": "25390",
    "wojewodztwo_id": "7",
    "miejscowosc_id": "9317",
    "miejscowosc": "Radom",
    "typ": "podstawowa",
    "nazwa": "Niepubliczna Szko\u0142a Podstawowa",
    "ulica": "Warszawska",
    "numer": "3",
    "kod": "26-600",
    "poczta": "Radom\r"
  },
  {
    "id": "25391",
    "wojewodztwo_id": "7",
    "miejscowosc_id": "9317",
    "miejscowosc": "Radom",
    "typ": "podstawowa",
    "nazwa": "Niepubliczna Szko\u0142a Podstawowa z Oddzia\u0142ami Przedszkolnymi Realizuj\u0105ca Program Rehabilitacji \"Nasza Szko\u0142a\"",
    "ulica": "Kr\u00f3lowej Jadwigi",
    "numer": "12",
    "kod": "26-600",
    "poczta": "Radom\r"
  },
  {
    "id": "25409",
    "wojewodztwo_id": "7",
    "miejscowosc_id": "9317",
    "miejscowosc": "Radom",
    "typ": "ponadgimnazjalna",
    "nazwa": "Niepubliczna Zasadnicza Szko\u0142a Zawodowa \"PROFESJA\" O\u015brodka Kszta\u0142cenia Zawodowego",
    "ulica": "Biznesowa",
    "numer": "7",
    "kod": "26-600",
    "poczta": "Radom\r"
  },
  {
    "id": "25410",
    "wojewodztwo_id": "7",
    "miejscowosc_id": "9317",
    "miejscowosc": "Radom",
    "typ": "ponadgimnazjalna",
    "nazwa": "Niepubliczna Zasadnicza Szko\u0142a Zawodowa ZDZ",
    "ulica": "Saska",
    "numer": "4\/6",
    "kod": "26-600",
    "poczta": "Radom\r"
  },
  {
    "id": "25406",
    "wojewodztwo_id": "7",
    "miejscowosc_id": "9317",
    "miejscowosc": "Radom",
    "typ": "gimnazjum",
    "nazwa": "Niepubliczne Gimnazjum",
    "ulica": "Warszawska",
    "numer": "3",
    "kod": "26-600",
    "poczta": "Radom\r"
  },
  {
    "id": "25405",
    "wojewodztwo_id": "7",
    "miejscowosc_id": "9317",
    "miejscowosc": "Radom",
    "typ": "gimnazjum",
    "nazwa": "Niepubliczne Gimnazjum O\u015brodka Kszta\u0142cenia Zawodowego \"PROFESJA\"",
    "ulica": "Biznesowa",
    "numer": "7",
    "kod": "26-600",
    "poczta": "Radom\r"
  },
  {
    "id": "25407",
    "wojewodztwo_id": "7",
    "miejscowosc_id": "9317",
    "miejscowosc": "Radom",
    "typ": "gimnazjum",
    "nazwa": "Niepubliczne Gimnazjum ZDZ",
    "ulica": "Saska",
    "numer": "4\/6",
    "kod": "26-600",
    "poczta": "Radom\r"
  },
  {
    "id": "25423",
    "wojewodztwo_id": "7",
    "miejscowosc_id": "9317",
    "miejscowosc": "Radom",
    "typ": "ponadgimnazjalna",
    "nazwa": "Niepubliczne Liceum Og\u00f3lnokszta\u0142c\u0105ce \"PROFESJA\" O\u015brodka Kszta\u0142cenia Zawodowego",
    "ulica": "Biznesowa",
    "numer": "7",
    "kod": "26-600",
    "poczta": "Radom\r"
  },
  {
    "id": "25424",
    "wojewodztwo_id": "7",
    "miejscowosc_id": "9317",
    "miejscowosc": "Radom",
    "typ": "ponadgimnazjalna",
    "nazwa": "Niepubliczne Liceum Og\u00f3lnokszta\u0142c\u0105ce ZDZ",
    "ulica": "Saska",
    "numer": "4\/6",
    "kod": "26-600",
    "poczta": "Radom\r"
  },
  {
    "id": "25427",
    "wojewodztwo_id": "7",
    "miejscowosc_id": "9317",
    "miejscowosc": "Radom",
    "typ": "ponadgimnazjalna",
    "nazwa": "Niepubliczne Technikum \"PROFESJA\" O\u015brodka Kszta\u0142cenia Zawodowego",
    "ulica": "Biznesowa",
    "numer": "7",
    "kod": "26-600",
    "poczta": "Radom\r"
  },
  {
    "id": "25428",
    "wojewodztwo_id": "7",
    "miejscowosc_id": "9317",
    "miejscowosc": "Radom",
    "typ": "ponadgimnazjalna",
    "nazwa": "Niepubliczne Technikum ZDZ",
    "ulica": "Saska",
    "numer": "6",
    "kod": "26-600",
    "poczta": "Radom\r"
  },
  {
    "id": "25365",
    "wojewodztwo_id": "7",
    "miejscowosc_id": "9317",
    "miejscowosc": "Radom",
    "typ": "podstawowa",
    "nazwa": "Publiczna Szko\u0142a Podstawowa Nr 1 z Oddzia\u0142ami Integracyjnymi",
    "ulica": "Odrodzenia",
    "numer": "37",
    "kod": "26-600",
    "poczta": "Radom\r"
  },
  {
    "id": "25366",
    "wojewodztwo_id": "7",
    "miejscowosc_id": "9317",
    "miejscowosc": "Radom",
    "typ": "podstawowa",
    "nazwa": "Publiczna Szko\u0142a Podstawowa Nr 13 z Oddzia\u0142ami Integracyjnymi ",
    "ulica": "Sienkiewicza",
    "numer": "30",
    "kod": "26-600",
    "poczta": "Radom\r"
  },
  {
    "id": "25441",
    "wojewodztwo_id": "7",
    "miejscowosc_id": "9317",
    "miejscowosc": "Radom",
    "typ": "podstawowa",
    "nazwa": "Publiczna Szko\u0142a Podstawowa Nr 14",
    "ulica": "Wierzbicka",
    "numer": "81\/83",
    "kod": "26-600",
    "poczta": "Radom\r"
  },
  {
    "id": "25367",
    "wojewodztwo_id": "7",
    "miejscowosc_id": "9317",
    "miejscowosc": "Radom",
    "typ": "podstawowa",
    "nazwa": "Publiczna Szko\u0142a Podstawowa Nr 15",
    "ulica": "Kielecka",
    "numer": "2\/6",
    "kod": "26-610",
    "poczta": "Radom\r"
  },
  {
    "id": "25368",
    "wojewodztwo_id": "7",
    "miejscowosc_id": "9317",
    "miejscowosc": "Radom",
    "typ": "podstawowa",
    "nazwa": "Publiczna Szko\u0142a Podstawowa Nr 17 im. Przyjaci\u00f3\u0142 Dzieci",
    "ulica": "Wierzbicka",
    "numer": "89\/93",
    "kod": "26-600",
    "poczta": "Radom\r"
  },
  {
    "id": "25432",
    "wojewodztwo_id": "7",
    "miejscowosc_id": "9317",
    "miejscowosc": "Radom",
    "typ": "podstawowa",
    "nazwa": "Publiczna Szko\u0142a Podstawowa Nr 18",
    "ulica": "Ofiar Firleja",
    "numer": "14",
    "kod": "26-600",
    "poczta": "Radom\r"
  },
  {
    "id": "25369",
    "wojewodztwo_id": "7",
    "miejscowosc_id": "9317",
    "miejscowosc": "Radom",
    "typ": "podstawowa",
    "nazwa": "Publiczna Szko\u0142a Podstawowa Nr 19",
    "ulica": "Energetyk\u00f3w",
    "numer": "10",
    "kod": "26-613",
    "poczta": "Radom\r"
  },
  {
    "id": "25370",
    "wojewodztwo_id": "7",
    "miejscowosc_id": "9317",
    "miejscowosc": "Radom",
    "typ": "podstawowa",
    "nazwa": "Publiczna Szko\u0142a Podstawowa Nr 2",
    "ulica": "Batalion\u00f3w Ch\u0142opskich",
    "numer": "16",
    "kod": "26-600",
    "poczta": "Radom\r"
  },
  {
    "id": "25371",
    "wojewodztwo_id": "7",
    "miejscowosc_id": "9317",
    "miejscowosc": "Radom",
    "typ": "podstawowa",
    "nazwa": "Publiczna Szko\u0142a Podstawowa Nr 20",
    "ulica": "Malenicka",
    "numer": "29",
    "kod": "26-600",
    "poczta": "Radom\r"
  },
  {
    "id": "25372",
    "wojewodztwo_id": "7",
    "miejscowosc_id": "9317",
    "miejscowosc": "Radom",
    "typ": "podstawowa",
    "nazwa": "Publiczna Szko\u0142a Podstawowa Nr 21",
    "ulica": "Troja\u0144ska",
    "numer": "5",
    "kod": "26-600",
    "poczta": "Radom\r"
  },
  {
    "id": "25373",
    "wojewodztwo_id": "7",
    "miejscowosc_id": "9317",
    "miejscowosc": "Radom",
    "typ": "podstawowa",
    "nazwa": "Publiczna Szko\u0142a Podstawowa Nr 23",
    "ulica": "Gajowa",
    "numer": "60",
    "kod": "26-600",
    "poczta": "Radom\r"
  },
  {
    "id": "25374",
    "wojewodztwo_id": "7",
    "miejscowosc_id": "9317",
    "miejscowosc": "Radom",
    "typ": "podstawowa",
    "nazwa": "Publiczna Szko\u0142a Podstawowa Nr 24",
    "ulica": "Powsta\u0144c\u00f3w \u015al\u0105skich",
    "numer": "4",
    "kod": "26-600",
    "poczta": "Radom\r"
  },
  {
    "id": "25375",
    "wojewodztwo_id": "7",
    "miejscowosc_id": "9317",
    "miejscowosc": "Radom",
    "typ": "podstawowa",
    "nazwa": "Publiczna Szko\u0142a Podstawowa Nr 25",
    "ulica": "Starokrakowska",
    "numer": "124\/128",
    "kod": "26-600",
    "poczta": "Radom\r"
  },
  {
    "id": "25376",
    "wojewodztwo_id": "7",
    "miejscowosc_id": "9317",
    "miejscowosc": "Radom",
    "typ": "podstawowa",
    "nazwa": "Publiczna Szko\u0142a Podstawowa Nr 26",
    "ulica": "Wo\u015bnicka",
    "numer": "125",
    "kod": "26-600",
    "poczta": "Radom\r"
  },
  {
    "id": "25377",
    "wojewodztwo_id": "7",
    "miejscowosc_id": "9317",
    "miejscowosc": "Radom",
    "typ": "podstawowa",
    "nazwa": "Publiczna Szko\u0142a Podstawowa Nr 28",
    "ulica": "Jaracza",
    "numer": "8",
    "kod": "26-600",
    "poczta": "Radom\r"
  },
  {
    "id": "25378",
    "wojewodztwo_id": "7",
    "miejscowosc_id": "9317",
    "miejscowosc": "Radom",
    "typ": "podstawowa",
    "nazwa": "Publiczna Szko\u0142a Podstawowa Nr 29 z Oddzia\u0142ami Integracyjnymi",
    "ulica": "Ceglana",
    "numer": "14",
    "kod": "26-600",
    "poczta": "Radom\r"
  },
  {
    "id": "25379",
    "wojewodztwo_id": "7",
    "miejscowosc_id": "9317",
    "miejscowosc": "Radom",
    "typ": "podstawowa",
    "nazwa": "Publiczna Szko\u0142a Podstawowa Nr 3",
    "ulica": "Sobieskiego",
    "numer": "12",
    "kod": "26-617",
    "poczta": "Radom\r"
  },
  {
    "id": "25380",
    "wojewodztwo_id": "7",
    "miejscowosc_id": "9317",
    "miejscowosc": "Radom",
    "typ": "podstawowa",
    "nazwa": "Publiczna Szko\u0142a Podstawowa Nr 31",
    "ulica": "Bia\u0142a",
    "numer": "6",
    "kod": "26-604",
    "poczta": "Radom\r"
  },
  {
    "id": "25381",
    "wojewodztwo_id": "7",
    "miejscowosc_id": "9317",
    "miejscowosc": "Radom",
    "typ": "podstawowa",
    "nazwa": "Publiczna Szko\u0142a Podstawowa Nr 32",
    "ulica": "Jarzy\u0144skiego",
    "numer": "3",
    "kod": "26-600",
    "poczta": "Radom\r"
  },
  {
    "id": "25382",
    "wojewodztwo_id": "7",
    "miejscowosc_id": "9317",
    "miejscowosc": "Radom",
    "typ": "podstawowa",
    "nazwa": "Publiczna Szko\u0142a Podstawowa Nr 33 ",
    "ulica": "Kolberga",
    "numer": "5",
    "kod": "26-600",
    "poczta": "Radom\r"
  },
  {
    "id": "25383",
    "wojewodztwo_id": "7",
    "miejscowosc_id": "9317",
    "miejscowosc": "Radom",
    "typ": "podstawowa",
    "nazwa": "Publiczna Szko\u0142a Podstawowa Nr 34",
    "ulica": "Mi\u0142a",
    "numer": "18",
    "kod": "26-600",
    "poczta": "Radom\r"
  },
  {
    "id": "25388",
    "wojewodztwo_id": "7",
    "miejscowosc_id": "9317",
    "miejscowosc": "Radom",
    "typ": "podstawowa",
    "nazwa": "Publiczna Szko\u0142a Podstawowa Nr 4 z Oddzia\u0142ami Integracyjnymi im. \u015bw. Kazimierza Jagiello\u0144czyka",
    "ulica": "Wy\u015bcigowa",
    "numer": "49",
    "kod": "26-600",
    "poczta": "Radom\r"
  },
  {
    "id": "25384",
    "wojewodztwo_id": "7",
    "miejscowosc_id": "9317",
    "miejscowosc": "Radom",
    "typ": "podstawowa",
    "nazwa": "Publiczna Szko\u0142a Podstawowa Nr 5 ",
    "ulica": "Gen. J. Sowi\u0144skiego",
    "numer": "1",
    "kod": "26-600",
    "poczta": "Radom\r"
  },
  {
    "id": "25385",
    "wojewodztwo_id": "7",
    "miejscowosc_id": "9317",
    "miejscowosc": "Radom",
    "typ": "podstawowa",
    "nazwa": "Publiczna Szko\u0142a Podstawowa Nr 6 ",
    "ulica": "Rapackiego",
    "numer": "24",
    "kod": "26-600",
    "poczta": "Radom\r"
  },
  {
    "id": "25386",
    "wojewodztwo_id": "7",
    "miejscowosc_id": "9317",
    "miejscowosc": "Radom",
    "typ": "podstawowa",
    "nazwa": "Publiczna Szko\u0142a Podstawowa Nr 7",
    "ulica": "Tybla",
    "numer": "7\/11",
    "kod": "26-600",
    "poczta": "Radom\r"
  },
  {
    "id": "25387",
    "wojewodztwo_id": "7",
    "miejscowosc_id": "9317",
    "miejscowosc": "Radom",
    "typ": "podstawowa",
    "nazwa": "Publiczna Szko\u0142a Podstawowa Nr 9 ",
    "ulica": "Sandomierska",
    "numer": "19",
    "kod": "26-600",
    "poczta": "Radom\r"
  },
  {
    "id": "25448",
    "wojewodztwo_id": "7",
    "miejscowosc_id": "9317",
    "miejscowosc": "Radom",
    "typ": "gimnazjum",
    "nazwa": "Publiczne Gimnazjum Nr 1",
    "ulica": "Staromiejska",
    "numer": "11",
    "kod": "26-600",
    "poczta": "Radom\r"
  },
  {
    "id": "25392",
    "wojewodztwo_id": "7",
    "miejscowosc_id": "9317",
    "miejscowosc": "Radom",
    "typ": "gimnazjum",
    "nazwa": "Publiczne Gimnazjum Nr 10 z Oddzia\u0142ami Integracyjnymi",
    "ulica": "D\u0142ugojowska",
    "numer": "10",
    "kod": "26-600",
    "poczta": "Radom\r"
  },
  {
    "id": "25393",
    "wojewodztwo_id": "7",
    "miejscowosc_id": "9317",
    "miejscowosc": "Radom",
    "typ": "gimnazjum",
    "nazwa": "Publiczne Gimnazjum Nr 11",
    "ulica": "Kujawska",
    "numer": "19",
    "kod": "26-600",
    "poczta": "Radom\r"
  },
  {
    "id": "25394",
    "wojewodztwo_id": "7",
    "miejscowosc_id": "9317",
    "miejscowosc": "Radom",
    "typ": "gimnazjum",
    "nazwa": "Publiczne Gimnazjum Nr 12",
    "ulica": "Krucza",
    "numer": "2\/10",
    "kod": "26-600",
    "poczta": "Radom\r"
  },
  {
    "id": "25395",
    "wojewodztwo_id": "7",
    "miejscowosc_id": "9317",
    "miejscowosc": "Radom",
    "typ": "gimnazjum",
    "nazwa": "Publiczne Gimnazjum Nr 13 z Oddzia\u0142ami Dwuj\u0119zycznymi",
    "ulica": "25 Czerwca",
    "numer": "79",
    "kod": "26-600",
    "poczta": "Radom\r"
  },
  {
    "id": "25442",
    "wojewodztwo_id": "7",
    "miejscowosc_id": "9317",
    "miejscowosc": "Radom",
    "typ": "gimnazjum",
    "nazwa": "Publiczne Gimnazjum Nr 14",
    "ulica": "Wierzbicka",
    "numer": "81\/83",
    "kod": "26-600",
    "poczta": "Radom\r"
  },
  {
    "id": "25396",
    "wojewodztwo_id": "7",
    "miejscowosc_id": "9317",
    "miejscowosc": "Radom",
    "typ": "gimnazjum",
    "nazwa": "Publiczne Gimnazjum Nr 2 z Oddzia\u0142ami Integracyjnymi ",
    "ulica": "Gagarina",
    "numer": "19",
    "kod": "26-600",
    "poczta": "Radom\r"
  },
  {
    "id": "25397",
    "wojewodztwo_id": "7",
    "miejscowosc_id": "9317",
    "miejscowosc": "Radom",
    "typ": "gimnazjum",
    "nazwa": "Publiczne Gimnazjum Nr 22 z Oddzia\u0142ami Integracyjnymi im. Karola Wojty\u0142y",
    "ulica": "Rapackiego",
    "numer": "24",
    "kod": "26-600",
    "poczta": "Radom\r"
  },
  {
    "id": "25445",
    "wojewodztwo_id": "7",
    "miejscowosc_id": "9317",
    "miejscowosc": "Radom",
    "typ": "gimnazjum",
    "nazwa": "Publiczne Gimnazjum Nr 23 z Oddzia\u0142ami Dwuj\u0119zycznymi ",
    "ulica": "Kili\u0144skiego",
    "numer": "25",
    "kod": "26-600",
    "poczta": "Radom\r"
  },
  {
    "id": "25398",
    "wojewodztwo_id": "7",
    "miejscowosc_id": "9317",
    "miejscowosc": "Radom",
    "typ": "gimnazjum",
    "nazwa": "Publiczne Gimnazjum Nr 3",
    "ulica": "Czarnoleska",
    "numer": "10",
    "kod": "26-600",
    "poczta": "Radom\r"
  },
  {
    "id": "25443",
    "wojewodztwo_id": "7",
    "miejscowosc_id": "9317",
    "miejscowosc": "Radom",
    "typ": "gimnazjum",
    "nazwa": "Publiczne Gimnazjum Nr 4 ",
    "ulica": "Osiedlowa",
    "numer": "36",
    "kod": "26-600",
    "poczta": "Radom\r"
  },
  {
    "id": "25399",
    "wojewodztwo_id": "7",
    "miejscowosc_id": "9317",
    "miejscowosc": "Radom",
    "typ": "gimnazjum",
    "nazwa": "Publiczne Gimnazjum Nr 5 ",
    "ulica": "Warszawska",
    "numer": "12",
    "kod": "26-600",
    "poczta": "Radom\r"
  },
  {
    "id": "25400",
    "wojewodztwo_id": "7",
    "miejscowosc_id": "9317",
    "miejscowosc": "Radom",
    "typ": "gimnazjum",
    "nazwa": "Publiczne Gimnazjum Nr 6",
    "ulica": "Sadkowska",
    "numer": "16",
    "kod": "26-600",
    "poczta": "Radom\r"
  },
  {
    "id": "25401",
    "wojewodztwo_id": "7",
    "miejscowosc_id": "9317",
    "miejscowosc": "Radom",
    "typ": "gimnazjum",
    "nazwa": "Publiczne Gimnazjum Nr 8 z Oddzia\u0142ami Integracyjnymi i Dwuj\u0119zycznymi",
    "ulica": "Piastowska",
    "numer": "17",
    "kod": "26-600",
    "poczta": "Radom\r"
  },
  {
    "id": "25408",
    "wojewodztwo_id": "7",
    "miejscowosc_id": "9317",
    "miejscowosc": "Radom",
    "typ": "gimnazjum",
    "nazwa": "Szko\u0142a Partnerstwa Mi\u0119dzynarodowego Gimnazjum J\u0119zykowe z Oddzia\u0142ami Dwuj\u0119zycznymi im. Unii Europejskiej",
    "ulica": "Traugutta",
    "numer": "34",
    "kod": "26-600",
    "poczta": "Radom\r"
  },
  {
    "id": "25425",
    "wojewodztwo_id": "7",
    "miejscowosc_id": "9317",
    "miejscowosc": "Radom",
    "typ": "ponadgimnazjalna",
    "nazwa": "Szko\u0142a Partnerstwa Mi\u0119dzynarodowego Og\u00f3lnokszta\u0142c\u0105ce Liceum J\u0119zykowe z Oddzia\u0142ami Dwuj\u0119zycznymi im. Unii Europejskiej",
    "ulica": "Traugutta",
    "numer": "34",
    "kod": "26-600",
    "poczta": "Radom\r"
  },
  {
    "id": "25429",
    "wojewodztwo_id": "7",
    "miejscowosc_id": "9317",
    "miejscowosc": "Radom",
    "typ": "ponadgimnazjalna",
    "nazwa": "Szko\u0142a Partnerstwa Mi\u0119dzynarodowego Technikum Ekonomiczno-Prawne z Oddzia\u0142ami Dwuj\u0119zycznymi im. Unii Europejskiej",
    "ulica": "Traugutta",
    "numer": "34",
    "kod": "26-600",
    "poczta": "Radom\r"
  },
  {
    "id": "25433",
    "wojewodztwo_id": "7",
    "miejscowosc_id": "9317",
    "miejscowosc": "Radom",
    "typ": "ponadgimnazjalna",
    "nazwa": "Technikum",
    "ulica": "Uniwersytecka",
    "numer": "6",
    "kod": "26-600",
    "poczta": "Radom\r"
  },
  {
    "id": "25435",
    "wojewodztwo_id": "7",
    "miejscowosc_id": "9317",
    "miejscowosc": "Radom",
    "typ": "ponadgimnazjalna",
    "nazwa": "Technikum ",
    "ulica": "Ko\u015bciuszki",
    "numer": "7",
    "kod": "26-600",
    "poczta": "Radom\r"
  },
  {
    "id": "25437",
    "wojewodztwo_id": "7",
    "miejscowosc_id": "9317",
    "miejscowosc": "Radom",
    "typ": "ponadgimnazjalna",
    "nazwa": "Technikum",
    "ulica": "Wernera",
    "numer": "22",
    "kod": "26-600",
    "poczta": "Radom\r"
  },
  {
    "id": "25439",
    "wojewodztwo_id": "7",
    "miejscowosc_id": "9317",
    "miejscowosc": "Radom",
    "typ": "ponadgimnazjalna",
    "nazwa": "Technikum",
    "ulica": "Sadkowska",
    "numer": "19",
    "kod": "26-600",
    "poczta": "Radom\r"
  },
  {
    "id": "25449",
    "wojewodztwo_id": "7",
    "miejscowosc_id": "9317",
    "miejscowosc": "Radom",
    "typ": "ponadgimnazjalna",
    "nazwa": "Technikum ",
    "ulica": "25 Czerwca",
    "numer": "66",
    "kod": "26-600",
    "poczta": "Radom\r"
  },
  {
    "id": "25451",
    "wojewodztwo_id": "7",
    "miejscowosc_id": "9317",
    "miejscowosc": "Radom",
    "typ": "ponadgimnazjalna",
    "nazwa": "Technikum ",
    "ulica": "\u015aniadeckich",
    "numer": "5",
    "kod": "26-600",
    "poczta": "Radom\r"
  },
  {
    "id": "25453",
    "wojewodztwo_id": "7",
    "miejscowosc_id": "9317",
    "miejscowosc": "Radom",
    "typ": "ponadgimnazjalna",
    "nazwa": "Technikum ",
    "ulica": "Armii Ludowej",
    "numer": "1",
    "kod": "26-600",
    "poczta": "Radom\r"
  },
  {
    "id": "25455",
    "wojewodztwo_id": "7",
    "miejscowosc_id": "9317",
    "miejscowosc": "Radom",
    "typ": "ponadgimnazjalna",
    "nazwa": "Technikum Elektryczne i Mechaniczne na podbudowie gimnazjum",
    "ulica": "Limanowskiego",
    "numer": "26\/30",
    "kod": "26-600",
    "poczta": "Radom\r"
  },
  {
    "id": "25457",
    "wojewodztwo_id": "7",
    "miejscowosc_id": "9317",
    "miejscowosc": "Radom",
    "typ": "ponadgimnazjalna",
    "nazwa": "Technikum o 4-letnim okresie nauczania",
    "ulica": "Al. Grzecznarowskiego",
    "numer": "2",
    "kod": "26-600",
    "poczta": "Radom\r"
  },
  {
    "id": "25430",
    "wojewodztwo_id": "7",
    "miejscowosc_id": "9317",
    "miejscowosc": "Radom",
    "typ": "ponadgimnazjalna",
    "nazwa": "Technikum TEB Edukacja",
    "ulica": "S\u0142owackiego",
    "numer": "84",
    "kod": "26-600",
    "poczta": "Radom\r"
  },
  {
    "id": "25415",
    "wojewodztwo_id": "7",
    "miejscowosc_id": "9317",
    "miejscowosc": "Radom",
    "typ": "ponadgimnazjalna",
    "nazwa": "V Liceum Og\u00f3lnokszta\u0142c\u0105ce z Oddzia\u0142ami Dwuj\u0119zycznymi",
    "ulica": "Traugutta",
    "numer": "52a",
    "kod": "26-600",
    "poczta": "Radom\r"
  },
  {
    "id": "25446",
    "wojewodztwo_id": "7",
    "miejscowosc_id": "9317",
    "miejscowosc": "Radom",
    "typ": "ponadgimnazjalna",
    "nazwa": "VI Liceum Og\u00f3lnokszta\u0142c\u0105ce z Oddzia\u0142ami Dwuj\u0119zycznymi",
    "ulica": "Kili\u0144skiego",
    "numer": "25",
    "kod": "26-600",
    "poczta": "Radom\r"
  },
  {
    "id": "25416",
    "wojewodztwo_id": "7",
    "miejscowosc_id": "9317",
    "miejscowosc": "Radom",
    "typ": "ponadgimnazjalna",
    "nazwa": "VII Liceum Og\u00f3lnokszta\u0142c\u0105ce",
    "ulica": "Powsta\u0144c\u00f3w Sl\u0105skich",
    "numer": "4",
    "kod": "26-615",
    "poczta": "Radom\r"
  },
  {
    "id": "25417",
    "wojewodztwo_id": "7",
    "miejscowosc_id": "9317",
    "miejscowosc": "Radom",
    "typ": "ponadgimnazjalna",
    "nazwa": "VIII Liceum Og\u00f3lnokszta\u0142c\u0105ce ",
    "ulica": "Sobieskiego",
    "numer": "12",
    "kod": "26-600",
    "poczta": "Radom\r"
  },
  {
    "id": "25418",
    "wojewodztwo_id": "7",
    "miejscowosc_id": "9317",
    "miejscowosc": "Radom",
    "typ": "ponadgimnazjalna",
    "nazwa": "X Liceum Og\u00f3lnokszta\u0142c\u0105ce",
    "ulica": "Beliny Pra\u017cmowskiego",
    "numer": "37",
    "kod": "26-600",
    "poczta": "Radom\r"
  },
  {
    "id": "25419",
    "wojewodztwo_id": "7",
    "miejscowosc_id": "9317",
    "miejscowosc": "Radom",
    "typ": "ponadgimnazjalna",
    "nazwa": "XI Liceum Og\u00f3lnokszta\u0142c\u0105ce z Oddzia\u0142ami Integracyjnymi im. Stanis\u0142awa Staszica",
    "ulica": "11 Listopada",
    "numer": "27",
    "kod": "26-600",
    "poczta": "Radom\r"
  },
  {
    "id": "25444",
    "wojewodztwo_id": "7",
    "miejscowosc_id": "9317",
    "miejscowosc": "Radom",
    "typ": "ponadgimnazjalna",
    "nazwa": "XII Liceum Og\u00f3lnokszta\u0142c\u0105ce",
    "ulica": "Osiedlowa",
    "numer": "36",
    "kod": "26-600",
    "poczta": "Radom\r"
  },
  {
    "id": "25426",
    "wojewodztwo_id": "7",
    "miejscowosc_id": "9317",
    "miejscowosc": "Radom",
    "typ": "ponadgimnazjalna",
    "nazwa": "Zaoczne Liceum Og\u00f3lnokszta\u0142c\u0105ce COSINUS",
    "ulica": "Sadkowska",
    "numer": "19",
    "kod": "26-600",
    "poczta": "Radom\r"
  },
  {
    "id": "25434",
    "wojewodztwo_id": "7",
    "miejscowosc_id": "9317",
    "miejscowosc": "Radom",
    "typ": "ponadgimnazjalna",
    "nazwa": "Zasadnicza Szko\u0142a Zawodowa ",
    "ulica": "Uniwersytecka",
    "numer": "6",
    "kod": "26-600",
    "poczta": "Radom\r"
  },
  {
    "id": "25436",
    "wojewodztwo_id": "7",
    "miejscowosc_id": "9317",
    "miejscowosc": "Radom",
    "typ": "ponadgimnazjalna",
    "nazwa": "Zasadnicza Szko\u0142a Zawodowa",
    "ulica": "Ko\u015bciuszki",
    "numer": "7",
    "kod": "26-600",
    "poczta": "Radom\r"
  },
  {
    "id": "25438",
    "wojewodztwo_id": "7",
    "miejscowosc_id": "9317",
    "miejscowosc": "Radom",
    "typ": "ponadgimnazjalna",
    "nazwa": "Zasadnicza Szko\u0142a Zawodowa",
    "ulica": "Wernera",
    "numer": "22",
    "kod": "26-600",
    "poczta": "Radom\r"
  },
  {
    "id": "25440",
    "wojewodztwo_id": "7",
    "miejscowosc_id": "9317",
    "miejscowosc": "Radom",
    "typ": "ponadgimnazjalna",
    "nazwa": "Zasadnicza Szko\u0142a Zawodowa",
    "ulica": "Sadkowska",
    "numer": "19",
    "kod": "26-600",
    "poczta": "Radom\r"
  },
  {
    "id": "25450",
    "wojewodztwo_id": "7",
    "miejscowosc_id": "9317",
    "miejscowosc": "Radom",
    "typ": "ponadgimnazjalna",
    "nazwa": "Zasadnicza Szko\u0142a Zawodowa ",
    "ulica": "25 Czerwca",
    "numer": "66",
    "kod": "26-600",
    "poczta": "Radom\r"
  },
  {
    "id": "25452",
    "wojewodztwo_id": "7",
    "miejscowosc_id": "9317",
    "miejscowosc": "Radom",
    "typ": "ponadgimnazjalna",
    "nazwa": "Zasadnicza Szko\u0142a Zawodowa ",
    "ulica": "\u015aniadeckich",
    "numer": "5",
    "kod": "26-600",
    "poczta": "Radom\r"
  },
  {
    "id": "25454",
    "wojewodztwo_id": "7",
    "miejscowosc_id": "9317",
    "miejscowosc": "Radom",
    "typ": "ponadgimnazjalna",
    "nazwa": "Zasadnicza Szko\u0142a Zawodowa",
    "ulica": "Armii Ludowej",
    "numer": "1",
    "kod": "26-600",
    "poczta": "Radom\r"
  },
  {
    "id": "25458",
    "wojewodztwo_id": "7",
    "miejscowosc_id": "9317",
    "miejscowosc": "Radom",
    "typ": "ponadgimnazjalna",
    "nazwa": "Zasadnicza Szko\u0142a Zawodowa",
    "ulica": "Al. Grzecznarowskiego",
    "numer": "2",
    "kod": "26-600",
    "poczta": "Radom\r"
  },
  {
    "id": "25431",
    "wojewodztwo_id": "7",
    "miejscowosc_id": "9317",
    "miejscowosc": "Radom",
    "typ": "ponadgimnazjalna",
    "nazwa": "Zasadnicza Szko\u0142a Zawodowa Nr 3 im. Janusza Korczaka",
    "ulica": "Al. Grzecznarowskiego",
    "numer": "15",
    "kod": "26-600",
    "poczta": "Radom\r"
  },
  {
    "id": "25456",
    "wojewodztwo_id": "7",
    "miejscowosc_id": "9317",
    "miejscowosc": "Radom",
    "typ": "ponadgimnazjalna",
    "nazwa": "Zasadnicza Szko\u0142a Zawodowa Ponadgimnazjalna",
    "ulica": "Limanowskiego",
    "numer": "26\/30",
    "kod": "26-600",
    "poczta": "Radom\r"
  }
]